LICENSE
MANIFEST.in
README.rst
setup.cfg
setup.py
ipython_animated_array/.DS_Store
ipython_animated_array/__init__.py
ipython_animated_array.egg-info/PKG-INFO
ipython_animated_array.egg-info/SOURCES.txt
ipython_animated_array.egg-info/dependency_links.txt
ipython_animated_array.egg-info/not-zip-safe
ipython_animated_array.egg-info/requires.txt
ipython_animated_array.egg-info/top_level.txt
ipython_animated_array/__pycache__/__init__.cpython-34.pyc
ipython_animated_array/template/animatetag.tpl.html