Metadata-Version: 1.1
Name: ipython-animated-array
Version: 1.0.0
Summary: animated array rendering on ipython-notebook (jupyter)
Home-page: https://github.com/airtoxin/ipython-animated-array
Author: Ryoji Ishii
Author-email: airtoxin@icloud.com
License: MIT
Keywords: ipython jupyter animation array
Platform: UNKNOWN
Classifier: Development Status :: 3 - Alpha
Classifier: License :: OSI Approved :: MIT License
Classifier: Programming Language :: Python
Classifier: Framework :: IPython
Classifier: Topic :: Scientific/Engineering :: Visualization
